warcbench/__init__.py
warcbench/config.py
warcbench/exceptions.py
warcbench/filters.py
warcbench/member_handlers.py
warcbench/models.py
warcbench/patches.py
warcbench/patterns.py
warcbench/record_handlers.py
warcbench/utils.py
warcbench/parsers/__init__.py
warcbench/parsers/gzipped_warc.py
warcbench/parsers/warc.py
warcbench/scripts/__init__.py
warcbench/scripts/compare_headers.py
warcbench/scripts/compare_parsers.py
warcbench/scripts/extract.py
warcbench/scripts/filter_records.py
warcbench/scripts/inspect.py
warcbench/scripts/match_record_pairs.py
warcbench/scripts/summarize.py
warcbench/scripts/utils.py
warcbench-0.1.0.dist-info/METADATA
warcbench-0.1.0.dist-info/WHEEL
warcbench-0.1.0.dist-info/entry_points.txt
warcbench-0.1.0.dist-info/licenses/LICENSE
warcbench-0.1.0.dist-info/RECORD
