Metadata-Version: 2.4
Name: warcbench
Version: 0.1.0
Summary: A tool for exploring, analyzing, transforming, recombining, and extracting data from WARC (Web ARChive) files
Project-URL: Repository, https://github.com/harvard-lil/warcbench
Project-URL: Bug Tracker, https://github.com/harvard-lil/warcbench/issues
Author-email: Harvard Library Innovation Lab <lil@law.harvard.edu>
License-File: LICENSE
Keywords: analysis,archive,harvard,library,parsing,warc,web-archive,web-crawling
Classifier: Development Status :: 3 - Alpha
Classifier: Intended Audience :: Developers
Classifier: Intended Audience :: Science/Research
Classifier: License :: OSI Approved :: MIT License
Classifier: Programming Language :: Python :: 3
Classifier: Programming Language :: Python :: 3.10
Classifier: Programming Language :: Python :: 3.11
Classifier: Programming Language :: Python :: 3.12
Classifier: Programming Language :: Python :: 3.13
Classifier: Topic :: Internet :: WWW/HTTP
Classifier: Topic :: Software Development :: Libraries :: Python Modules
Classifier: Topic :: System :: Archiving
Classifier: Topic :: Text Processing :: Markup :: HTML
Requires-Python: >=3.10
Requires-Dist: brotli>=1.1.0
Requires-Dist: click>=8.1.8
Requires-Dist: pyzstd>=0.16.2
